websauna.tests-1.0a8-py3.6-nspkg.pth
websauna/tests/__init__.py
websauna/tests/demotasks.py
websauna/tests/fixtures.py
websauna/tests/scaffold.py
websauna/tests/sitemapsamples.py
websauna/tests/utils.py
websauna/tests/webserver.py
websauna.tests-1.0a8.dist-info/DESCRIPTION.rst
websauna.tests-1.0a8.dist-info/METADATA
websauna.tests-1.0a8.dist-info/RECORD
websauna.tests-1.0a8.dist-info/WHEEL
websauna.tests-1.0a8.dist-info/entry_points.txt
websauna.tests-1.0a8.dist-info/metadata.json
websauna.tests-1.0a8.dist-info/namespace_packages.txt
websauna.tests-1.0a8.dist-info/top_level.txt
