Metadata-Version: 2.0
Name: websauna.tests
Version: 1.0a8
Summary: Test fixtures for Websauna
Home-page: https://github.com/websauna/websauna.tests
Author: Erico Andrei
Author-email: erico@tokenmarket.net
License: MIT
Keywords: pyramid pytest websauna
Platform: UNKNOWN
Classifier: Development Status :: 4 - Beta
Classifier: Framework :: Pyramid
Classifier: Framework :: Pytest
Classifier: Intended Audience :: Developers
Classifier: License :: OSI Approved :: MIT License
Classifier: Operating System :: OS Independent
Classifier: Programming Language :: Python :: 3
Classifier: Programming Language :: Python :: 3.5
Classifier: Programming Language :: Python :: 3.6
Classifier: Programming Language :: Python :: Implementation :: CPython
Classifier: Programming Language :: Python
Classifier: Topic :: Software Development :: Testing
Requires-Dist: codecov
Requires-Dist: flake8
Requires-Dist: flaky
Requires-Dist: isort
Requires-Dist: plaster
Requires-Dist: pyramid
Requires-Dist: pytest-cov
Requires-Dist: pytest-runner
Requires-Dist: pytest-splinter
Requires-Dist: pytest-timeout
Requires-Dist: pytest (>=3.1.1)
Requires-Dist: sqlalchemy
Requires-Dist: transaction
Requires-Dist: websauna.system
Requires-Dist: webtest
Provides-Extra: dev
Requires-Dist: pyroma (==2.2); extra == 'dev'
Requires-Dist: sphinx (>=1.6.1); extra == 'dev'
Requires-Dist: sphinx-autodoc-typehints; extra == 'dev'
Requires-Dist: sphinx-rtd-theme; extra == 'dev'
Requires-Dist: sphinxcontrib-zopeext; extra == 'dev'
Requires-Dist: zest.releaser[recommended]; extra == 'dev'
